ekumenlabs_config/__init__.py
ekumenlabs_config/exceptions.py
ekumenlabs_config/models.py
ekumenlabs_config-0.1.1.dist-info/LICENSE
ekumenlabs_config-0.1.1.dist-info/METADATA
ekumenlabs_config-0.1.1.dist-info/WHEEL
ekumenlabs_config-0.1.1.dist-info/RECORD
