Metadata-Version: 2.1
Name: ekumenlabs-config
Version: 0.1.1
Summary: 
Home-page: https://github.com/Ekumen-OS/ekumenlabs_config
License: MIT
Keywords: configuration
Author: Guillermo Manzato
Author-email: manzato@ekumenlabs.com
Requires-Python: >=3.10,<4.0
Classifier: Development Status :: 4 - Beta
Classifier: Framework :: AsyncIO
Classifier: Intended Audience :: Developers
Classifier: License :: OSI Approved :: MIT License
Classifier: Programming Language :: Python :: 3
Classifier: Programming Language :: Python :: 3.10
Classifier: Programming Language :: Python :: 3.11
Requires-Dist: tortoise-orm (>=0.19.2,<0.20.0)
Project-URL: Documentation, https://github.com/Ekumen-OS/ekumenlabs_config
Project-URL: Repository, https://github.com/Ekumen-OS/ekumenlabs_config
